{
  "_static": {
    "generator": {
      "name": "@globus/static-data-portal"
    }
  },
  "data": {
    "version": "1.0.0",
    "attributes": {
      "content": {
        "title": "Globus Compliance Portal",
        "privacy_policy": "See the Globus Privacy policy at https://www.globus.org/legal/privacy",
        "terms_of_service": "This is an example terms of service – you should replace this with your own terms."
      },
      "globus": {
        "application": {
          "client_id": "e9c63589-16f4-4bef-b96f-c6cfe8fe59b3"
        },
        "transfer": {
          "collection_id": "1e5ab660-9945-4fd6-b3e7-98064952e114",
          "path": "/"
        }
      }
    }
  },

  "branding": {
    "logo": "assets/Globus_logo_BLUE_horizontal.png",
    "title": "Globus Logo",
    "subtitle": "Blue Horizontal"
  }
}
